LICENSE
MANIFEST.in
README.md
pyproject.toml
requirements.txt
setup.cfg
setup.py
versioneer.py
extras/pyuftp
pyuftp/__init__.py
pyuftp/_version.py
pyuftp/authenticate.py
pyuftp/base.py
pyuftp/client.py
pyuftp/cp.py
pyuftp/cryptutils.py
pyuftp/pconnector.py
pyuftp/share.py
pyuftp/uftp.py
pyuftp/utils.py
pyuftp.egg-info/PKG-INFO
pyuftp.egg-info/SOURCES.txt
pyuftp.egg-info/dependency_links.txt
pyuftp.egg-info/entry_points.txt
pyuftp.egg-info/requires.txt
pyuftp.egg-info/top_level.txt