Metadata-Version: 2.4
Name: pyuftp
Version: 1.0.5
Summary: UFTP (UNICORE FTP) commandline client
Home-page: https://github.com/UNICORE-EU/pyuftp
Author: Bernd Schuller
Author-email: b.schuller@fz-juelich.de
License: License :: OSI Approved :: BSD
Requires-Python: >=3.7
License-File: LICENSE
Requires-Dist: requests>=2.5.1
Requires-Dist: pyjwt[crypto]>=2.8.0
Requires-Dist: bcrypt>=4.0.0
Requires-Dist: pycryptodome>=3.20.0
Dynamic: author
Dynamic: author-email
Dynamic: description
Dynamic: description-content-type
Dynamic: home-page
Dynamic: license
Dynamic: license-file
Dynamic: requires-dist
Dynamic: requires-python
Dynamic: summary
